pynetcom/__init__.py
pynetcom/cli_client.py
pynetcom/netconf_client.py
pynetcom/rest_nce.py
pynetcom/rest_nsp.py
pynetcom/utils/cli_parser.py
pynetcom/utils/huawei_router_tools.py
pynetcom/utils/util.py
pynetcom-0.1.6.dist-info/METADATA
pynetcom-0.1.6.dist-info/WHEEL
pynetcom-0.1.6.dist-info/top_level.txt
pynetcom-0.1.6.dist-info/RECORD
