Metadata-Version: 2.1
Name: pynetcom
Version: 0.1.6
Summary: Library for Huawei, Nokia network device API interactions
Home-page: https://github.com/ddarth/pynetcom
Author: Dmitriy Kozlov
Author-email: kdsarts@gmail.com
Keywords: networking huawei nokia rest cli netconf
Classifier: Development Status :: 4 - Beta
Classifier: Intended Audience :: Developers
Classifier: Intended Audience :: System Administrators
Classifier: Intended Audience :: Telecommunications Industry
Classifier: License :: OSI Approved :: MIT License
Classifier: Operating System :: OS Independent
Classifier: Programming Language :: Python :: 3
Classifier: Programming Language :: Python :: 3.7
Classifier: Programming Language :: Python :: 3.8
Classifier: Programming Language :: Python :: 3.9
Classifier: Programming Language :: Python :: 3.10
Classifier: Programming Language :: Python :: 3.11
Classifier: Topic :: System :: Networking
Classifier: Topic :: System :: Networking :: Monitoring
Classifier: Topic :: Software Development :: Libraries
Requires-Python: >=3.7
Requires-Dist: requests
Requires-Dist: urllib3
Requires-Dist: ncclient
Requires-Dist: xmltodict
Requires-Dist: wexpect-venv
